<?xml version="1.0" encoding="utf-8"?>
<odoo>
    <data noupdate="1">
        <record id="teams_menu" model="website.menu">
            <field name="name">Equipes</field>
            <field name="url">/page/teams</field>
            <field name="parent_id" ref="website.main_menu" />
            <field name="sequence" type="int">20</field>
            <field name="website_id" ref="website.default_website"/>
        </record>

        <record id="website.menu_contactus" model="website.menu">
            <field name="name">Contact</field>
            <field name="url">/page/contactus</field>
            <field name="parent_id" ref="website.menu_homepage" />
            <field name="sequence" type="int">40</field>
            <field name="website_id" ref="website.default_website"/>
        </record>

        <record id="club_menu" model="website.menu">
            <field name="name">Club</field>
            <field name="url">/page/club</field>
            <field name="parent_id" ref="website.menu_homepage" />
            <field name="sequence" type="int">20</field>
            <field name="website_id" ref="website.default_website"/>
        </record>

        <record id="baseball_menu" model="website.menu">
            <field name="name">Baseball</field>
            <field name="url">/page/baseball</field>
            <field name="parent_id" ref="website.menu_homepage" />
            <field name="sequence" type="int">30</field>
            <field name="website_id" ref="website.default_website"/>
        </record>

        <record id="register_menu" model="website.menu">
            <field name="name">S'inscrire</field>
            <field name="url">/page/register</field>
            <field name="parent_id" ref="website.menu_homepage" />
            <field name="sequence" type="int">35</field>
            <field name="website_id" ref="website.default_website"/>
        </record>

        <record id="upcoming_games_menu" model="website.menu">
            <field name="name">Matches</field>
            <field name="url">/page/upcoming_games</field>
            <field name="parent_id" ref="website.menu_homepage" />
            <field name="sequence" type="int">10</field>
            <field name="website_id" ref="website.default_website"/>
        </record>

        <record id="website_sale.menu_shop" model="website.menu">
            <field name="sequence" type="int">25</field>
        </record>

        <record id="website_menu_sponsors" model="website.menu">
            <field name="name">Partenaires</field>
            <field name="url">/sponsors</field>
            <field name="parent_id" ref="website.menu_homepage" />
            <field name="sequence" type="int">37</field>
            <field name="website_id" ref="website.default_website"/>
        </record>

        <record id="website_menu_coachcorner" model="website.menu">
            <field name="name">Coach's corner</field>
            <field name="url">/coach/drill</field>
            <field name="parent_id" ref="website.menu_homepage" />
            <field name="sequence" type="int">39</field>
            <field name="website_id" ref="website.default_website"/>
        </record>

    </data>
</odoo>